city_scrapers_core/__init__.py
city_scrapers_core/constants.py
city_scrapers_core/decorators.py
city_scrapers_core/items.py
city_scrapers_core/utils.py
city_scrapers_core/commands/__init__.py
city_scrapers_core/commands/combinefeeds.py
city_scrapers_core/commands/genspider.py
city_scrapers_core/commands/runall.py
city_scrapers_core/commands/validate.py
city_scrapers_core/extensions/__init__.py
city_scrapers_core/extensions/azure_storage.py
city_scrapers_core/extensions/status.py
city_scrapers_core/pipelines/__init__.py
city_scrapers_core/pipelines/default.py
city_scrapers_core/pipelines/diff.py
city_scrapers_core/pipelines/meeting.py
city_scrapers_core/pipelines/ocd.py
city_scrapers_core/pipelines/validation.py
city_scrapers_core/spiders/__init__.py
city_scrapers_core/spiders/legistar.py
city_scrapers_core/spiders/spider.py
city_scrapers_core/templates/spider.tmpl
city_scrapers_core/templates/spider_legistar.tmpl
city_scrapers_core/templates/test.tmpl
city_scrapers_core/templates/test_legistar.tmpl
tests/__init__.py
tests/test_commands.py
tests/test_pipelines.py
tests/test_spiders.py
city_scrapers_core-0.10.1.dist-info/LICENSE
city_scrapers_core-0.10.1.dist-info/METADATA
city_scrapers_core-0.10.1.dist-info/WHEEL
city_scrapers_core-0.10.1.dist-info/top_level.txt
city_scrapers_core-0.10.1.dist-info/RECORD
