Metadata-Version: 2.1
Name: city-scrapers-core
Version: 0.10.1
Summary: Core functionality for City Scrapers projects
Home-page: https://github.com/City-Bureau/city-scrapers-core
Author: City Bureau
Author-email: documenters@citybureau.org
License: MIT
Platform: UNKNOWN
Classifier: Programming Language :: Python :: 3
Classifier: License :: OSI Approved :: MIT License
Classifier: Operating System :: OS Independent
Classifier: Framework :: Scrapy
Requires-Python: >=3.6,<4.0
Requires-Dist: jsonschema (>=3.0.0a5)
Requires-Dist: pytz
Requires-Dist: requests
Requires-Dist: scrapy
Provides-Extra: aws
Requires-Dist: boto3 ; extra == 'aws'
Provides-Extra: azure
Requires-Dist: azure-storage-blob (>=12) ; extra == 'azure'
Provides-Extra: gcs
Requires-Dist: google-cloud-storage ; extra == 'gcs'
